rawg_export_user_collections/__init__.py
rawg_export_user_collections/main.py
rawg_export_user_collections/models.py
rawg_export_user_collections-0.0.2.dist-info/entry_points.txt
rawg_export_user_collections-0.0.2.dist-info/LICENSE
rawg_export_user_collections-0.0.2.dist-info/WHEEL
rawg_export_user_collections-0.0.2.dist-info/METADATA
rawg_export_user_collections-0.0.2.dist-info/RECORD
