Metadata-Version: 2.1
Name: rawg-export-user-collections
Version: 0.0.2
Summary: Export public user's collections from the rawg.io video game database.
License: MIT
Author: TauSynth
Author-email: the.dark.neutronium.tau.synth@gmail.com
Requires-Python: >=3.10,<4.0
Classifier: License :: OSI Approved :: MIT License
Classifier: Programming Language :: Python :: 3
Classifier: Programming Language :: Python :: 3.10
Requires-Dist: aiohttp[speedups] (>=3.8.3,<4.0.0)
Requires-Dist: pydantic (>=1.10.2,<2.0.0)
